Metadata-Version: 2.1
Name: grzegorz_test_sda
Version: 0.1
Summary: Opis
Home-page: http://google.pl
